dpiste/__init__.py
dpiste/__main__.py
dpiste/compare_dicom.py
dpiste/dicom2png.py
dpiste/get_dicom.py
dpiste/p02_initial_extraction.py
dpiste/p03_validated_extraction.py
dpiste/p06_mammogram_extraction.py
dpiste/p08_mammogram_deidentification.py
dpiste/p08_test_deid_df2dicom.py
dpiste/p08_test_mammogram_deid.py
dpiste/p11_hdh_data_transfer.py
dpiste/p11_hdh_encryption.py
dpiste/p11_screening_extraction_id_temp.py
dpiste/p12_SNDS_match.py
dpiste/report.py
dpiste/script_cnam.py
dpiste/setup.py
dpiste/testEsis.py
dpiste/utils.py
dpiste/dal/__init__.py
dpiste/dal/cnam.py
dpiste/dal/crcdc.py
dpiste/dal/esis.py
dpiste/dal/neoscope.py
dpiste/dal/screening.py
dpiste/dal/utils.py
dpiste/data/esis.xml
dpiste/data/sparkly-maven-paths.url
dpiste/data/reports/dcm4chee-import.md
dpiste/data/reports/esis-import.md
dpiste/data/reports/neo-stats.md
dpiste/data/reports/screening-stats.md
deep_piste-0.0.18.dist-info/LICENCE
deep_piste-0.0.18.dist-info/METADATA
deep_piste-0.0.18.dist-info/WHEEL
deep_piste-0.0.18.dist-info/top_level.txt
deep_piste-0.0.18.dist-info/RECORD
