Metadata-Version: 2.1
Name: deep-piste
Version: 0.0.18
Summary: Evaluating the impact of IA on Breast Cancer Screening Program
Home-page: https://github.com/Epiconcept-Paris/deep.piste
Author: Francisco Orchard
Author-email: f.orchard@epiconcept.fr
License: GNU General Public License v2.0
Platform: UNKNOWN
License-File: LICENCE
Requires-Dist: kskit
Requires-Dist: clipboard
Requires-Dist: pyarrow
Requires-Dist: ipykernel
Requires-Dist: nbconvert
Requires-Dist: jupytext
Requires-Dist: plotly
Requires-Dist: python-gnupg
Requires-Dist: fabric
Requires-Dist: paramiko
